{
  "50": "In the Hands of the Fans",
  "49": "49",
  "48": "48",
  "47": "47",
  "46": "46",
  "45": "45",
  "44": "44",
  "43": "43",
  "42": "42",
  "41": "41",
  "40": "Winners at War",
  "39": "Island of the Idols",
  "38": "Edge of Extinction",
  "37": "David vs. Goliath",
  "36": "Ghost Island",
  "35": "Heroes vs. Healers vs. Hustlers",
  "34": "Game Changers",
  "33": "Millennials vs. Gen X",
  "32": "Kaoh Rong",
  "31": "Cambodia",
  "30": "Worlds Apart",
  "29": "San Juan del Sur",
  "28": "Cagayan",
  "27": "Blood vs. Water",
  "26": "Caramoan",
  "25": "Philippines",
  "24": "One World",
  "23": "South Pacific",
  "22": "Redemption Island",
  "21": "Nicaragua",
  "20": "Heroes vs. Villains",
  "19": "Samoa",
  "18": "Tocantins",
  "17": "Gabon",
  "16": "Micronesia",
  "15": "China",
  "14": "Fiji",
  "13": "Cook Islands",
  "12": "Panama",
  "11": "Guatemala",
  "10": "Palau",
  "9": "Vanuatu",
  "8": "All-Stars",
  "7": "Pearl Islands",
  "6": "The Amazon",
  "5": "Thailand",
  "4": "Marquesas",
  "3": "Africa",
  "2": "The Australian Outback",
  "1": "Borneo"
}